hrm/__init__.py
hrm/__main__.py
hrm/levels.json
hrm/parse.py
hrm/solutions.json
hrm/tui.py
hrm_interpreter-1.4.2.dist-info/METADATA
hrm_interpreter-1.4.2.dist-info/WHEEL
hrm_interpreter-1.4.2.dist-info/entry_points.txt
hrm_interpreter-1.4.2.dist-info/licenses/LICENSE
hrm_interpreter-1.4.2.dist-info/RECORD
