Metadata-Version: 2.1
Name: hrm-interpreter
Version: 1.4.2
Summary: Minimalist Human Resource Machine interpreter
Project-URL: Homepage, https://github.com/fpom/hrm
Project-URL: Bug Tracker, https://github.com/fpom/hrm/issues
Author-email: Franck Pommereau <franck.pommereau@univ-evry.fr>
License-Expression: MIT
License-File: LICENSE
Classifier: Development Status :: 4 - Beta
Classifier: Intended Audience :: Developers
Classifier: License :: OSI Approved :: MIT License
Classifier: Operating System :: OS Independent
Classifier: Programming Language :: Python :: 3.9
Classifier: Topic :: Software Development :: Interpreters
Requires-Python: >=3.9
Requires-Dist: rich[all]
Requires-Dist: typer[all]
